Metadata-Version: 2.1
Name: storii
Version: 1.0
Summary: Build little ascii friends that can speak and move
Home-page: https://github.com/guillaumefe/storii
Author: Guillaume Fe
Author-email: guillaume.ferron@gmail.com
License: UNKNOWN
Platform: UNKNOWN
Classifier: Programming Language :: Python :: 3
Classifier: License :: OSI Approved :: GNU General Public License v3 or later (GPLv3+)
Classifier: Operating System :: OS Independent
Requires-Python: >=3.6
